pytest_venv/__init__.py
pytest_venv-0.3.dist-info/LICENSE.txt
pytest_venv-0.3.dist-info/METADATA
pytest_venv-0.3.dist-info/WHEEL
pytest_venv-0.3.dist-info/entry_points.txt
pytest_venv-0.3.dist-info/top_level.txt
pytest_venv-0.3.dist-info/RECORD
