Metadata-Version: 2.1
Name: pytest-venv
Version: 0.3
Summary: py.test fixture for creating a virtual environment
Home-page: https://github.com/mmerickel/pytest-venv
Author: Michael Merickel
Author-email: michael@merickel.org
Classifier: Development Status :: 4 - Beta
Classifier: Framework :: Pytest
Classifier: Intended Audience :: Developers
Classifier: License :: OSI Approved :: MIT License
Classifier: Natural Language :: English
Classifier: Programming Language :: Python :: 3
Classifier: Programming Language :: Python :: 3.7
Classifier: Programming Language :: Python :: 3.8
Classifier: Programming Language :: Python :: 3.9
Classifier: Programming Language :: Python :: 3.10
Classifier: Programming Language :: Python :: 3.11
Classifier: Programming Language :: Python :: 3.12
Classifier: Programming Language :: Python :: Implementation :: CPython
Classifier: Programming Language :: Python :: Implementation :: PyPy
Classifier: Topic :: Software Development :: Testing
License-File: LICENSE.txt
Requires-Dist: packaging
Requires-Dist: pytest
Requires-Dist: virtualenv
Provides-Extra: testing
Requires-Dist: coverage ; extra == 'testing'
